usepy/__init__.py
usepy/converter/__init__.py
usepy/converter/to_bool.py
usepy/converter/to_list.py
usepy/converter/to_md5.py
usepy/converter/to_set.py
usepy/converter/to_string.py
usepy/date/__init__.py
usepy/date/format.py
usepy/date/now.py
usepy/date/parse.py
usepy/date/timestamp.py
usepy/decorator/__init__.py
usepy/decorator/catch_error.py
usepy/decorator/retry.py
usepy/decorator/singleton.py
usepy/decorator/throttle.py
usepy/dict/__init__.py
usepy/dict/ad_dict.py
usepy/dict/merge_dicts.py
usepy/dict/sort_by_key.py
usepy/dict/sort_by_value.py
usepy/list/__init__.py
usepy/list/chunk.py
usepy/list/compact.py
usepy/list/count_by.py
usepy/list/difference.py
usepy/list/every.py
usepy/list/first.py
usepy/list/flatten.py
usepy/list/flatten_deep.py
usepy/list/key_by.py
usepy/list/last.py
usepy/list/sample.py
usepy/list/shuffle.py
usepy/list/some.py
usepy/list/union.py
usepy/list/uniq.py
usepy/list/without.py
usepy/list/zip_dict.py
usepy/list/zip_tuple.py
usepy/misc/__init__.py
usepy/misc/dynamic_import.py
usepy/misc/get_function_name.py
usepy/string/__init__.py
usepy/string/_get_section.py
usepy/string/_get_words.py
usepy/string/camel_case.py
usepy/string/capitalize.py
usepy/string/kebab_case.py
usepy/string/left.py
usepy/string/lower_case.py
usepy/string/middle.py
usepy/string/middle_batch.py
usepy/string/pascal_case.py
usepy/string/right.py
usepy/string/snake_case.py
usepy/typing_.py
usepy/validator/__init__.py
usepy/validator/is_async_function.py
usepy/validator/is_url.py
usepy-0.4.21.dist-info/METADATA
usepy-0.4.21.dist-info/WHEEL
usepy-0.4.21.dist-info/RECORD
