Metadata-Version: 2.3
Name: usepy
Version: 0.4.21
Summary: usepy
Author: miclon
Author-email: jcnd@163.com
Requires-Python: >=3.7,<4.0
Classifier: Programming Language :: Python :: 3
Classifier: Programming Language :: Python :: 3.7
Classifier: Programming Language :: Python :: 3.8
Classifier: Programming Language :: Python :: 3.9
Classifier: Programming Language :: Python :: 3.10
Classifier: Programming Language :: Python :: 3.11
Classifier: Programming Language :: Python :: 3.12
Classifier: Programming Language :: Python :: 3.13
Requires-Dist: typing-extensions (>=4.0.0,<5.0.0) ; python_version == "3.6"
Requires-Dist: typing-extensions (>=4.5.0,<5.0.0) ; python_version >= "3.7"
Project-URL: Homepage, https://usepy.code05.com/
